boomcode/__init__.py
boomcode/boomcode.py
boomcode-0.1.1.dist-info/LICENSE
boomcode-0.1.1.dist-info/METADATA
boomcode-0.1.1.dist-info/WHEEL
boomcode-0.1.1.dist-info/top_level.txt
boomcode-0.1.1.dist-info/RECORD
