Metadata-Version: 2.2
Name: boomcode
Version: 0.1.1
Summary: A fun, cool prank package that is easy to code in.
Home-page: https://github.com/daredevilmonkeyface/boomcode
Author: daredevilmonkeyface (AKA daredevilmonke)
Classifier: Programming Language :: Python :: 3
Classifier: Intended Audience :: Developers
Classifier: Topic :: Software Development :: Libraries :: Python Modules
Classifier: License :: OSI Approved :: MIT License
Classifier: Operating System :: Microsoft :: Windows
Requires-Python: >=3.6
License-File: LICENSE
Requires-Dist: pyautogui
Requires-Dist: pywin32
Dynamic: author
Dynamic: classifier
Dynamic: description
Dynamic: description-content-type
Dynamic: home-page
Dynamic: requires-dist
Dynamic: requires-python
Dynamic: summary
